crisphello/__init__.py
crisphello-0.0.1.dist-info/METADATA
crisphello-0.0.1.dist-info/WHEEL
crisphello-0.0.1.dist-info/top_level.txt
crisphello-0.0.1.dist-info/RECORD
