Metadata-Version: 2.1
Name: crisphello
Version: 0.0.1
Summary: This is a simple python package that is built for testing purpose.
Author: Crispen Gari
Author-email: <crispengari@gmail.com>
License: UNKNOWN
Keywords: python,hello,math
Platform: UNKNOWN
Classifier: Development Status :: 1 - Planning
Classifier: Intended Audience :: Developers
Classifier: Programming Language :: Python :: 3
Classifier: Operating System :: Unix
Classifier: Operating System :: MacOS :: MacOS X
Classifier: Operating System :: Microsoft :: Windows
